LICENSE
README.md
setup.cfg
setup.py
mkdocs_roamlinks_eostrebis_plugin/__init__.py
mkdocs_roamlinks_eostrebis_plugin/plugin.py
mkdocs_roamlinks_eostrebis_plugin.egg-info/PKG-INFO
mkdocs_roamlinks_eostrebis_plugin.egg-info/SOURCES.txt
mkdocs_roamlinks_eostrebis_plugin.egg-info/dependency_links.txt
mkdocs_roamlinks_eostrebis_plugin.egg-info/entry_points.txt
mkdocs_roamlinks_eostrebis_plugin.egg-info/requires.txt
mkdocs_roamlinks_eostrebis_plugin.egg-info/top_level.txt
tests/__init__.py
tests/test_plugin.py