Metadata-Version: 2.1
Name: mkdocs-roamlinks-eostrebis-plugin
Version: 0.2.1
Summary: An MkDocs plugin
Home-page: https://github.com/Jackiexiao/eostrebis-roamlinks-plugin
Author: frosqh
Author-email: frosqh@gmail.com
License: MIT
Keywords: mkdocs
Classifier: Development Status :: 4 - Beta
Classifier: Intended Audience :: Developers
Classifier: Intended Audience :: Information Technology
Classifier: License :: OSI Approved :: MIT License
Classifier: Programming Language :: Python
Classifier: Programming Language :: Python :: 3.6
Classifier: Programming Language :: Python :: 3.7
Requires-Python: >=3.6
License-File: LICENSE
Requires-Dist: mkdocs>=1.0.4
Requires-Dist: unidecode>=1.3.8
Provides-Extra: dev
Requires-Dist: pytest; extra == "dev"
